neo3crypto.cpython-314-aarch64-linux-musl.so
neo3crypto.libs/libgcc_s-2d945d6c.so.1
neo3crypto.libs/libstdc++-85f2cd6d.so.6.0.33
neo3crypto-0.4.5.dist-info/METADATA
neo3crypto-0.4.5.dist-info/WHEEL
neo3crypto-0.4.5.dist-info/top_level.txt
neo3crypto-0.4.5.dist-info/RECORD
neo3crypto-0.4.5.dist-info/licenses/LICENSE.txt
neo3crypto-0.4.5.dist-info/sboms/auditwheel.cdx.json
