Metadata-Version: 2.4
Name: neo3crypto
Version: 0.4.5
Summary: Native crypto functions for the NEO 3 Blockchain
Home-page: https://github.com/CityOfZion/neo3crypto
Author: Erik van den Brink
Author-email: erik@coz.io
License: MIT
Classifier: Development Status :: 4 - Beta
Classifier: Intended Audience :: Developers
Classifier: Programming Language :: Python :: 3.13
Classifier: Programming Language :: C++
Requires-Python: >=3.13.0,<3.15
License-File: LICENSE.txt
Dynamic: author
Dynamic: author-email
Dynamic: classifier
Dynamic: description
Dynamic: description-content-type
Dynamic: home-page
Dynamic: license
Dynamic: license-file
Dynamic: requires-python
Dynamic: summary
